{
  "tabPane": [
    {
      "title": "SmartDashboard",
      "autoPopulate": true,
      "autoPopulatePrefix": "SmartDashboard/",
      "widgetPane": {
        "gridSize": 128.0,
        "showGrid": true,
        "hgap": 16.0,
        "vgap": 16.0,
        "titleType": 0,
        "tiles": {
          "0,0": {
            "size": [
              1,
              1
            ],
            "content": {
              "_type": "Text View",
              "_source0": "network_table:///SmartDashboard/Speed Mode",
              "_title": "Speed Mode",
              "_glyph": 132,
              "_showGlyph": true
            }
          },
          "0,1": {
            "size": [
              1,
              1
            ],
            "content": {
              "_type": "Boolean Box",
              "_source0": "network_table:///SmartDashboard/Field Relieve",
              "_title": "Field Relieve",
              "_glyph": 26,
              "_showGlyph": true,
              "Colors/Color when true": "#7CFC00FF",
              "Colors/Color when false": "#8B0000FF"
            }
          },
          "1,0": {
            "size": [
              2,
              2
            ],
            "content": {
              "_type": "Gyro",
              "_source0": "network_table:///SmartDashboard/Heading Degrees",
              "_title": "Heading Degrees",
              "_glyph": 139,
              "_showGlyph": true,
              "Visuals/Major tick spacing": 45.0,
              "Visuals/Starting angle": 180.0,
              "Visuals/Show tick mark ring": true,
              "Visuals/Counter clockwise": false
            }
          },
          "9,1": {
            "size": [
              1,
              1
            ],
            "content": {
              "_type": "Text View",
              "_source0": "network_table:///SmartDashboard/Drive Controller",
              "_title": "Drive Controller",
              "_glyph": 0,
              "_showGlyph": false
            }
          },
          "3,0": {
            "size": [
              1,
              2
            ],
            "content": {
              "_type": "Number Bar",
              "_source0": "network_table:///SmartDashboard/Robot Speed",
              "_title": "Robot Speed",
              "_glyph": 152,
              "_showGlyph": true,
              "Range/Min": 0.0,
              "Range/Max": 60.0,
              "Range/Center": 0.0,
              "Visuals/Num tick marks": 5,
              "Visuals/Show text": true,
              "Visuals/Orientation": "VERTICAL"
            }
          },
          "9,0": {
            "size": [
              1,
              1
            ],
            "content": {
              "_type": "Boolean Box",
              "_source0": "network_table:///SmartDashboard/ControlActive",
              "_title": "ControlActive",
              "_glyph": 148,
              "_showGlyph": false,
              "Colors/Color when true": "#7CFC00FF",
              "Colors/Color when false": "#8B0000FF"
            }
          },
          "9,2": {
            "size": [
              1,
              1
            ],
            "content": {
              "_type": "Text View",
              "_source0": "network_table:///SmartDashboard/Bot Name",
              "_title": "Bot Name",
              "_glyph": 148,
              "_showGlyph": false
            }
          }
        }
      }
    },
    {
      "title": "LiveWindow",
      "autoPopulate": true,
      "autoPopulatePrefix": "LiveWindow/",
      "widgetPane": {
        "gridSize": 128.0,
        "showGrid": true,
        "hgap": 16.0,
        "vgap": 16.0,
        "titleType": 0,
        "tiles": {}
      }
    }
  ],
  "windowGeometry": {
    "x": -7.199999809265137,
    "y": -7.199999809265137,
    "width": 1550.4000244140625,
    "height": 830.4000244140625
  }
}